{"cameraMode":{"drawMode":0,"name":"Shaded","section":"Shading Mode"},"sceneLighting":true,"audioPlay":false,"sceneViewState":{"showFog":true,"showMaterialUpdate":false,"showSkybox":true,"showFlares":true,"showImageEffects":true,"showParticleSystems":true},"in2DMode":false,"pivot":{"x":3.375943660736084,"y":-8.496101379394532,"z":-29.312480926513673},"rotation":{"x":-0.4987872540950775,"y":-0.01741047576069832,"z":0.010017317719757557,"w":-0.8665035367012024},"size":20.544918060302736,"orthographic":false}